extract_pdf_content.py
pdf_cli.py
pdf_processing_system-1.0.1.dist-info/licenses/LICENSE
pdf_processing_system-1.0.1.dist-info/METADATA
pdf_processing_system-1.0.1.dist-info/WHEEL
pdf_processing_system-1.0.1.dist-info/entry_points.txt
pdf_processing_system-1.0.1.dist-info/top_level.txt
pdf_processing_system-1.0.1.dist-info/RECORD
