Metadata-Version: 2.4
Name: pdf-processing-system
Version: 1.0.1
Summary: Comprehensive PDF content extraction and intelligent splitting system
Home-page: https://github.com/goliathuy/pdf-extractor
Author: goliathuy
Author-email: goliathuy <aug1381-goliathuy@yahoo.com>
Project-URL: Homepage, https://github.com/goliathuy/pdf-extractor
Project-URL: Bug Reports, https://github.com/goliathuy/pdf-extractor/issues
Project-URL: Source, https://github.com/goliathuy/pdf-extractor
Project-URL: Documentation, https://github.com/goliathuy/pdf-extractor#readme
Project-URL: Changelog, https://github.com/goliathuy/pdf-extractor/blob/main/CHANGELOG.md
Keywords: pdf,extraction,text,images,splitting,cli,processing
Classifier: Development Status :: 5 - Production/Stable
Classifier: Intended Audience :: Developers
Classifier: Topic :: Office/Business :: Office Suites
Classifier: Topic :: Text Processing :: Filters
Classifier: Topic :: Multimedia :: Graphics :: Graphics Conversion
Classifier: License :: OSI Approved :: MIT License
Classifier: Programming Language :: Python :: 3
Classifier: Programming Language :: Python :: 3.8
Classifier: Programming Language :: Python :: 3.9
Classifier: Programming Language :: Python :: 3.10
Classifier: Programming Language :: Python :: 3.11
Classifier: Programming Language :: Python :: 3.12
Classifier: Operating System :: OS Independent
Requires-Python: >=3.8
License-File: LICENSE
Requires-Dist: PyMuPDF>=1.23.0
Requires-Dist: Pillow>=9.0.0
Requires-Dist: psutil>=5.9.0
Provides-Extra: dev
Requires-Dist: pytest>=7.0; extra == "dev"
Requires-Dist: pytest-cov; extra == "dev"
Requires-Dist: black; extra == "dev"
Requires-Dist: flake8; extra == "dev"
Requires-Dist: mypy; extra == "dev"
Provides-Extra: test
Requires-Dist: pytest>=7.0; extra == "test"
Requires-Dist: pytest-cov; extra == "test"
Dynamic: author
Dynamic: home-page
Dynamic: license-file
Dynamic: requires-python
